repello_argus_client/__init__.py
repello_argus_client/client.py
repello_argus_client/errors.py
repello_argus_client/enums/__init__.py
repello_argus_client/enums/core.py
repello_argus_client/internal/__init__.py
repello_argus_client/internal/http_client.py
repello_argus_client/internal/validation.py
repello_argus_client/tracing/__init__.py
repello_argus_client/tracing/context.py
repello_argus_client/tracing/tracer.py
repello_argus_client/tracing/types.py
repello_argus_client/types/__init__.py
repello_argus_client/types/core.py
repello_argus_client-0.2.4.dist-info/licenses/LICENSE
repello_argus_client-0.2.4.dist-info/METADATA
repello_argus_client-0.2.4.dist-info/WHEEL
repello_argus_client-0.2.4.dist-info/top_level.txt
repello_argus_client-0.2.4.dist-info/RECORD
