Metadata-Version: 2.4
Name: repello-argus-client
Version: 0.2.4
Summary: The official Python SDK for the Repello Argus API.
Author-email: Aaditya Gupta <aadityagupta400@gmail.com>, Naman Mishra <naman@repello.ai>
License: 
Project-URL: Homepage, https://github.com/Repello-AI/argus-sdk-client
Project-URL: Repository, https://github.com/Repello-AI/argus-sdk-client
Project-URL: Bug Tracker, https://github.com/Repello-AI/argus-sdk-client/issues
Keywords: repello,argus,api,sdk,safety
Classifier: Programming Language :: Python :: 3
Classifier: License :: OSI Approved :: Apache Software License
Classifier: Operating System :: OS Independent
Classifier: Development Status :: 3 - Alpha
Classifier: Intended Audience :: Developers
Classifier: Topic :: Software Development :: Libraries :: Python Modules
Requires-Python: >=3.8
License-File: LICENSE
Requires-Dist: httpx>=0.25.0
Requires-Dist: tenacity>=8.2.0
Requires-Dist: pydantic>=2.0
Provides-Extra: test
Requires-Dist: pytest>=7.0; extra == "test"
Requires-Dist: pytest-cov>=4.0; extra == "test"
Requires-Dist: pytest-mock>=3.10; extra == "test"
Requires-Dist: pytest-asyncio; extra == "test"
Provides-Extra: dev
Requires-Dist: repello-argus-client[test]; extra == "dev"
Requires-Dist: ruff; extra == "dev"
Requires-Dist: black; extra == "dev"
Requires-Dist: pre-commit; extra == "dev"
Dynamic: license-file
